BeginnersbookKotlinJiaochengChuyi/README.md
BeginnersbookKotlinJiaochengChuyi/__init__.py
BeginnersbookKotlinJiaochengChuyi/__main__.py
BeginnersbookKotlinJiaochengChuyi/file.epub
BeginnersbookKotlinJiaochengChuyi/index.html
BeginnersbookKotlinJiaochengChuyi/css/__init__.py
BeginnersbookKotlinJiaochengChuyi/css/annotations.css
BeginnersbookKotlinJiaochengChuyi/css/main.css
BeginnersbookKotlinJiaochengChuyi/css/normalize.css
BeginnersbookKotlinJiaochengChuyi/css/popup.css
BeginnersbookKotlinJiaochengChuyi/font/__init__.py
BeginnersbookKotlinJiaochengChuyi/font/fontello.eot
BeginnersbookKotlinJiaochengChuyi/font/fontello.svg
BeginnersbookKotlinJiaochengChuyi/font/fontello.ttf
BeginnersbookKotlinJiaochengChuyi/font/fontello.woff
BeginnersbookKotlinJiaochengChuyi/img/__init__.py
BeginnersbookKotlinJiaochengChuyi/img/annotator-glyph-sprite.png
BeginnersbookKotlinJiaochengChuyi/img/annotator-icon-sprite.png
BeginnersbookKotlinJiaochengChuyi/img/apple-touch-icon.png
BeginnersbookKotlinJiaochengChuyi/img/cancelfullscreen.png
BeginnersbookKotlinJiaochengChuyi/img/close.png
BeginnersbookKotlinJiaochengChuyi/img/fullscreen.png
BeginnersbookKotlinJiaochengChuyi/img/loader.gif
BeginnersbookKotlinJiaochengChuyi/img/menu-icon.png
BeginnersbookKotlinJiaochengChuyi/img/save.png
BeginnersbookKotlinJiaochengChuyi/img/saved.png
BeginnersbookKotlinJiaochengChuyi/img/settings-s.png
BeginnersbookKotlinJiaochengChuyi/img/settings.png
BeginnersbookKotlinJiaochengChuyi/img/star.png
BeginnersbookKotlinJiaochengChuyi/js/__init__.py
BeginnersbookKotlinJiaochengChuyi/js/epub.js
BeginnersbookKotlinJiaochengChuyi/js/epub.min.js
BeginnersbookKotlinJiaochengChuyi/js/epub.min.map
BeginnersbookKotlinJiaochengChuyi/js/hooks.min.js
BeginnersbookKotlinJiaochengChuyi/js/hooks.min.map
BeginnersbookKotlinJiaochengChuyi/js/reader.js
BeginnersbookKotlinJiaochengChuyi/js/reader.js.map
BeginnersbookKotlinJiaochengChuyi/js/reader.min.js
BeginnersbookKotlinJiaochengChuyi/js/reader.min.map
beginnersbook_kotlin_jiaocheng_chuyi-2024.3.5.0.dist-info/METADATA
beginnersbook_kotlin_jiaocheng_chuyi-2024.3.5.0.dist-info/WHEEL
beginnersbook_kotlin_jiaocheng_chuyi-2024.3.5.0.dist-info/entry_points.txt
beginnersbook_kotlin_jiaocheng_chuyi-2024.3.5.0.dist-info/top_level.txt
beginnersbook_kotlin_jiaocheng_chuyi-2024.3.5.0.dist-info/RECORD
